{
"name" : "Bonobo's Foods",
"status" : "",
"link" : "https://bonobosfoods.com/", 
"hours" : "(Tuesday - Friday: 11:00 - 19:00), (Saturday: 11:00 - 17:00)", 
"tel" : "807-345-6262", 
"sms": "", 
"address" : "493 Oliver Road", 
"map": "https://maps.app.goo.gl/wmWsUNiQXMgmHt469", 
"updated" : "2025-10-30", 
"courtesy" : "Justin Menu",
"text" : "
VEGGIE BURGERS Served on fresh whole wheat buns from Donato's Bakery
<br>1. PICK A PATTY V
<br>100% Plant-based
<br>SEED
<br>WILD RICE NUT
<br>CHICK BEAN NUT
<br>APPLE MUSTARD CHICK'N
<br>BEYOND MEAT
<br>2. PICK A STYLE
<br>BONOBO V 10$ House made garlic aioli, ketchup, onion, pickle, tomato, and field greens
<br>MUSHROOM MELT 11$ House made garlic aioli, crimini mushrooms, Thunder Oak gouda, tomato, and field greens
<br>BARBECUE V 11$ House made garlic aioli, fried onion slivers, house barbecue sauce, tomato, and field greens
<br>3. UPGRADE YOUR BURGER
<br>GOUDA/DAIYA CHEESE 2$
<br>AVOCADO 2$
<br>ONION SLIVERS 1$
<br>SMOKY MAPLE TEMPEH 2$
<br>SAUTÉED MUSHROOMS 1$
<br>CRISPY BREADED JALAPEÑOS 2$
<br>4. ADD A SIDE
<br>SALAD 6$
<br>FRIES 5$
<br>POUTINE 10$
<br>V - Already Vegan Substitute gouda with vegan cheese to make the entire menu vegan. GLUTEN FREE BUN 1$
<br>AVOCADO PESTO TOAST V 8$ Donato's whole wheat bread with avocado, house-made pesto, seed mix, hemp hearts and sprouts
<br>CASHEW CREAM VEG. SOUP V 11$ With pesto toast
<br>CORN DOGS V 12$ 2 corn dogs with your choice of dip
<br>FISH TACOS V 15$ Three tacos on corn tortillas with greens, creamy coleslaw, mango salsa, chipotle aioli and ''fish''
<br>T.L.T. BURGER V 10$ House-made garlic aioli, smoky maple bacon tempeh, tomato, and field greens
<br>MANGO CHICK'N BURGER V 11$ Apple mustard chick'n patty, maple BBQ sauce, coleslaw, and mango
<br>BBQ CHICK'N BURGER V 10$ House-made garlic aioli, breaded chick'n, maple BBQ sauce, tomato, and field greens
<br>VEGAN MAC BURGER V 11$ Beyond Meat patties, house mac sauce, diced onions, shredded lettuce, pickles, and vegan cheddar
<br>LOADED MAC FRIES V 12$ / 16$ Diced onions & pickles, mac sauce, shredded lettuce, and chopped Beyond Meat patty with vegan cheddar on a bed of fries
<br>SALADS
<br>ADD: avocado 2$, almond pesto 4$, grilled seitan chick'n 4$
<br>SWEET V 14$ Strawberry, mango, kiwi, fresh sprouts, sunflower/pumpkin seeds, hemp hearts, coconut, almonds, cashews. With house poppy seed dressing
<br>SAVOURY 14$ Snap peas, fresh sprouts, cherry tomatoes, tofu, sunflower/pumpkin seeds, hemp hearts, almonds, cashews, gouda. With house sun-dried tomato dressing
<br>MEDITERRANEAN 14$ Olives, fresh sprouts, cucumber, cherry tomatoes, snap peas, red onion, almonds, cashews, gouda. With house creamy cashew dill dressing
<br>APPETIZERS
<br>MAC & CHZ CASHEW BITES V 12$ With garlic aioli
<br>CAULIFLOWER PAKORAS V 12$ With sweet chili sauce
<br>FRIES V 5$ / 7$ Garlic / chipotle aioli or house-made gravy
<br>POUTINE 10$ / 13$ Gouda curds topped with house-made gravy
<br>SPICY POUTINE 12$ / 15$ Our poutine with chipotle gravy, crispy onion slivers and heartbeat Hot Sauce
<br>FOR KIDS
<br>GRILLED CHEESE 7$ Donato's whole wheat bread with gouda
<br>CRISPY TENDERS & FRIES V 10$ Gardein Chick'n fingers & fries with a choice of dip
<br>DESSERT
<br>Dine in only
<br>DEEP FRIED BANANA 10$ With CASHEW ICE CREAM V Banana, deep fried, served with cashew ice cream and drizzled with local maple syrup
<br>All prices & ingredients are subject to change.
"
}