{
"name" : "Sarah and Dipity's",
"status" : "",
"link" : "https://sarahanddipitys.com/", 
"hours" : "", 
"tel" : "mailto: support@sarahanddipitys.com", 
"sms": "", 
"address" : "Address: 14 Balsam Street (George's Market)
<br>&nbsp;&nbsp;&nbsp;&nbsp; 111 Frederica Street East (Westfort Foods)
<br>&nbsp;&nbsp;&nbsp;&nbsp; 301 Pearl Street (Maltese Grocery)", 
"map": "", 
"updated" : "Updated: 2025-08-20", 
"courtesy" : "Courtesy: Justin Menu", 
"text" : "Individual Items
<br>
<br>Pita Chips
<br>a bag of our baked pita chips
<br>$5.00
<br>
<br>S’more Pretzel
<br>1 soft pretzel, coated in cinnamon sugar topped
<br>with marshmallow and chocolate
<br>$4.00
<br>
<br>Brownies
<br>2 homemade brownies (chocolate
<br>chips inside, chocolate ganache on
<br>the top with candy coated
<br>chocolate sprinkles)
<br>$4.00
<br>
<br>Artisan Loaf
<br>medium size round artisan loaf, pairs pleasantly
<br>with our Spinach Dip and Chips To Go
<br>$5.00
<br>
<br>Chips (pita/tortilla)
<br>a mixed bag of our baked pita and tortilla chips
<br>$5.00
<br>
<br>Tortilla Chips
<br>a bag of our baked tortilla chips
<br>$5.00
<br>
<br>Frozen
<br>
<br>Herb & Garlic Soft Pretzel Sticks with Marinara
<br>8 herb and garlic soft pretzel sticks with marinara.
<br>Comes frozen, ready to heat and serve.
<br>$12.50
<br>
<br>Mini Pretzels and Beer Cheese Dip
<br>6 mini, salted, buttered soft pretzels with beer
<br>cheese dip. Comes frozen, ready to heat and serve.
<br>$12.50
<br>
<br>New Products
<br>
<br>Blueberry Lemon Twists
<br>This box contains 4 blueberry lemon
<br>soft pretzel twists, topped with a
<br>lemon glaze
<br>$12.00
<br>
<br>Lemon Poppy Seed Twists
<br>This box contains 4 lemon poppy
<br>seed soft pretzel twists, topped with
<br>a lemon glaze
<br>$12.50
<br>
<br>Ginger Snap Cookies
<br>12 of our homemade Ginger Snap Cookies. Crisp,
<br>chewy and flavourful.
<br>$13.50
<br>
<br>Ice Cream
<br>
<br>Strawberry Shortcake Ice Cream Box
<br>A box of 4 of our homemade
<br>strawberry shortcake ice cream
<br>bars.
<br>$18.00
<br>
<br>Dips
<br>
<br>Sprinkle Dip Box
<br>A box with sprinkle dip, cinnamon
<br>bites, homemade cookies.
<br>$18.00
<br>
<br>Taco Dip and Chips To Go
<br>Taco Dip (vegetarian friendly) comes with
<br>homemade tortilla chips
<br>$15.00
<br>
<br>Avocado Hummus (8oz)
<br>An 8 oz container of creamy
<br>avocado hummus
<br>$6.50
<br>
<br>Sprinkle Dip (8oz)
<br>Our sprinkle dip in a 8 oz container.
<br>$9.50
<br>
<br>Spinach Dip Box
<br>This box includes 1 artisan bread
<br>bowl, cut and filled with our cheesy
<br>spinach dip. We recommend you
<br>(eat as is, or cook at 350F for 20
<br>min until warm inside or warm)
<br>$20.00
<br>
<br>Skor Dip (8 oz)
<br>Our cream cheese based dip, with skor bits and
<br>caramel. Pairs well with apples, fruit, cookies and
<br>more!
<br>$9.50
<br>
<br>Herb and Garlic Cream Cheese Dip (8oz)
<br>Our herb and garlic cream cheese dip, pairs well
<br>with soft pretzels, chips and more!
<br>$9.50
<br>
<br>Spinach Dip and Chips To Go
<br>Our homemade cheesy spinach dip!
<br>Comes with homemade pitas and
<br>tortilla chips.
<br>$13.00
<br>
<br>Soft Pretzels
<br>
<br>Box of 10 Cinnamon Sugar Mini Pretzels
<br>A box of 10 mini pretzels each coated in cinnamon
<br>sugar
<br>$22.00
<br>
<br>Cinnamon Sugar Pretzel Bites
<br>A bag of our cinnamon sugar pretzel bites
<br>$13.00
<br>
<br>Box of 10 Plain Mini Pretzels
<br>A box of 10 plain mini-pretzels, salted and buttered
<br>$22.00
<br>
<br>Cinnamon Sugar Pretzels (6 in a bag)
<br>6 soft pretzels dusted with
<br>cinnamon sugar
<br>$20.00
<br>
<br>Plain Butter Pretzels (6 in a bag)
<br>6 soft pretzels buttered and salted
<br>$20.00
<br>
<br>Everything Pretzels (6 in a bag)
<br>6 soft everything pretzels (egg wash
<br>and coated with everything
<br>seasoning)
<br>$20.00
<br>
<br>Salted Pretzel Bites
<br>A bag of our salted pretzel bites
<br>$13.00
<br>
<br>Pizza Pretzels (6 in a bag)
<br>6 soft pizza pretzels (pizza sauce,
<br>spices, parmesan cheese)
<br>$23.00
<br>
<br>Soft Pretzel Knots
<br>A bag of 6 plain (salted and buttered) pretzel knots
<br>$9.00",
"image0" : "img0.webp",
"image1" : "img1.webp"
}